{"Siri":{"$":{"xmlns:ns2":"http://www.ifopt.org.uk/acsb","xmlns":"http://www.siri.org.uk/siri","xmlns:ns4":"http://datex2.eu/schema/1_0/1_0","xmlns:ns3":"http://www.ifopt.org.uk/ifopt"},"ServiceDelivery":[{"ResponseTimestamp":["2018-07-23T09:28:02.9614573-04:00"],"SituationExchangeDelivery":[{"ResponseTimestamp":["2018-07-23T09:28:02.9614573-04:00"],"Status":["true"],"Situations":[{"PtSituationElement":[{"CreationTime":["2018-07-23T09:27:38.597-04:00"],"SituationNumber":["\r\n                  MTA NYCT_dce5f9bd-41a3-4e42-b57a-05294a879775"],"PublicationWindow":[{"StartTime":["2018-07-23T06:47:00-04:00"]}],"Summary":[{"_":"Northbound [N] and [W] trains are running with delays because of signal problems at Queensboro Plaza.","$":{"xml:lang":"EN"}}],"Description":[{"_":"Northbound [N] and [W] trains are running with delays because of signal problems at Queensboro Plaza.","$":{"xml:lang":"EN"}}],"LongDescription":["<P>Northbound [N] and [W] trains are running with delays because of signal problems at <STRONG>Queensboro Plaza.</STRONG></P>\r\n<P>Our crews are on the scene making repairs and we hope to resume normal service soon.</P>"],"Planned":["false"],"ReasonName":["Delays"],"MessagePriority":["2"],"Source":[{"SourceType":["directReport"]}],"Affects":[{"VehicleJourneys":[{"AffectedVehicleJourney":[{"LineRef":["\r\n                      MTA NYCT_N"],"DirectionRef":["0"]},{"LineRef":["\r\n                      MTA NYCT_W"],"DirectionRef":["0"]}]}]}],"Consequences":[{"Consequence":[{"Condition":["delayed"],"Severity":["undefined"]}]}]},{"CreationTime":["2018-07-23T09:08:24.92-04:00"],"SituationNumber":["\r\n                  MTA NYCT_8ca37754-85e8-4e6a-a005-62913bcad8a2"],"PublicationWindow":[{"StartTime":["2018-07-23T08:41:00-04:00"],"EndTime":["2018-07-23T09:30:00-04:00"]}],"Summary":[{"_":"[N] and [Q] train service has resumed after a train's brakes were automatically activated at Times Sq-42 St.","$":{"xml:lang":"EN"}}],"Description":[{"_":"[N] and [Q] train service has resumed after a train's brakes were automatically activated at Times Sq-42 St.","$":{"xml:lang":"EN"}}],"LongDescription":["[N] and [Q] train service has resumed after a train's brakes were automatically activated at <STRONG>Times Sq-42 St.</STRONG>"],"Planned":["false"],"ReasonName":["Delays"],"MessagePriority":["2"],"Source":[{"SourceType":["directReport"]}],"Affects":[{"VehicleJourneys":[{"AffectedVehicleJourney":[{"LineRef":["\r\n                      MTA NYCT_N"],"DirectionRef":["0"]},{"LineRef":["\r\n                      MTA NYCT_Q"],"DirectionRef":["0"]}]}]}],"Consequences":[{"Consequence":[{"Condition":["delayed"],"Severity":["undefined"]}]}]},{"CreationTime":["2018-07-23T00:00:00-04:00"],"SituationNumber":["\r\n                  MTA NYCT_194095"],"PublicationWindow":[{"StartTime":["2018-07-23T00:00:00-04:00"],"EndTime":["2018-08-17T23:59:00-04:00"]}],"Summary":[{"_":"TRACK REPLACEMENT  Jul 23  - Aug 17, Mon to Fri, 945 AM to 330 PM","$":{"xml:lang":"EN"}}],"Description":[{"_":"TRACK REPLACEMENT  Jul 23  - Aug 17, Mon to Fri, 945 AM to 330 PM","$":{"xml:lang":"EN"}}],"LongDescription":["<a class=\"plannedWorkDetailLink\" onclick=ShowHide(194095);><b>TRACK REPLACEMENT | Jul 23 - Aug 17, Mon to Fri, 9:45 AM to 3:30 PM </b>(except Aug 1 & 16)<br clear=left></font><b>Woodlawn-bound [4] trains skip 183 St, Fordham Rd, Kingsbridge Rd and Bedford Pk Blvd in the Bronx</a><br/><br/><div id= 194095 class=\"plannedWorkDetail\" ><br></b>For service <i>to</i> these stations, take the [4]<b> </b>to Mosholu Pkwy and transfer to a Crown Hts-bound [4].<br><br></font>For service <i>from</i> these stations, take the [4] to Burnside Av and transfer to a Woodlawn-bound [4].<br><br><table class=plannedworkTableStyle  border=1 cellspacing=1 cellpadding=5 rules=none frame=box><td>  [ad]  <td><font size=1>This service change affects one or more ADA accessible stations. Please call 511 for help with planning your trip. If you are deaf or hard of hearing, use your preferred relay service provider or the free 711 relay.  </font></table><br><b><br></div></b><br/>"],"Planned":["true"],"ReasonName":["Planned Work"],"MessagePriority":["\r\n                  1\r\n                "],"Source":[{"SourceType":["directReport"]}],"Affects":[{"VehicleJourneys":[{"AffectedVehicleJourney":[{"LineRef":["\r\n                      MTA NYCT_4"],"DirectionRef":["0"]}]}]}],"Consequences":[{"Consequence":[{"Condition":["diverted"],"Severity":["undefined"]}]}]},{"CreationTime":["2018-07-23T00:00:00-04:00"],"SituationNumber":["\r\n                  MTA NYCT_195706"],"PublicationWindow":[{"StartTime":["2018-07-23T00:00:00-04:00"],"EndTime":["2018-07-23T23:59:00-04:00"]}],"Summary":[{"_":"TRACK MAINTENANCE   Jul 23, Monday, 945 AM to 1 PM  Brooklyn Bridge-bound [6D] trains run local from Parkchester to 3 Av-138 St in the Bronx","$":{"xml:lang":"EN"}}],"Description":[{"_":"TRACK MAINTENANCE   Jul 23, Monday, 945 AM to 1 PM  Brooklyn Bridge-bound [6D] trains run local from Parkchester to 3 Av-138 St in the Bronx","$":{"xml:lang":"EN"}}],"LongDescription":["<a class=\"plannedWorkDetailLink\" onclick=ShowHide(195706);><b>TRACK MAINTENANCE | Jul 23, Monday, 9:45 AM to 1 PM</font><br clear=left>Brooklyn Bridge-bound [6D] trains run local from Parkchester to 3 Av-138 St in the Bronx</a><br/><br/><div id= 195706 class=\"plannedWorkDetail\" ><br></div></b><br/>"],"Planned":["true"],"ReasonName":["Planned Work"],"MessagePriority":["\r\n                  1\r\n                "],"Source":[{"SourceType":["directReport"]}],"Affects":[{"VehicleJourneys":[{"AffectedVehicleJourney":[{"LineRef":["\r\n                      MTA NYCT_6"],"DirectionRef":["1"]}]}]}],"Consequences":[{"Consequence":[{"Condition":["altered"],"Severity":["undefined"]}]}]},{"CreationTime":["2018-07-23T00:00:00-04:00"],"SituationNumber":["\r\n                  MTA NYCT_195705"],"PublicationWindow":[{"StartTime":["2018-07-23T00:00:00-04:00"],"EndTime":["2018-07-23T23:59:00-04:00"]}],"Summary":[{"_":"TRACK MAINTENANCE   Jul 23, Monday, 945 AM to 330 PM  Brooklyn Bridge-bound [6] trains run express from Pelham Bay Park to Parkchester in the Bronx","$":{"xml:lang":"EN"}}],"Description":[{"_":"TRACK MAINTENANCE   Jul 23, Monday, 945 AM to 330 PM  Brooklyn Bridge-bound [6] trains run express from Pelham Bay Park to Parkchester in the Bronx","$":{"xml:lang":"EN"}}],"LongDescription":["<a class=\"plannedWorkDetailLink\" onclick=ShowHide(195705);><b>TRACK MAINTENANCE | Jul 23, Monday, 9:45 AM to 3:30 PM</font><br clear=left>Brooklyn Bridge-bound [6] trains run express from Pelham Bay Park to Parkchester in the Bronx</a><br/><br/><div id= 195705 class=\"plannedWorkDetail\" ><br></b>For service <i>to</i> Buhre Av, Middletown Rd, Westchester Sq, Zerega and Castle Hill Avs, take the [6] to Parkchester and transfer to a Pelham Bay Park-bound [6].<br><br>For service <i>from</i> these stations take the [6] to Pelham Bay Park and transfer to a Brooklyn Bridge-bound [6].<br><b><br></div></b><br/>"],"Planned":["true"],"ReasonName":["Planned Work"],"MessagePriority":["\r\n                  1\r\n                "],"Source":[{"SourceType":["directReport"]}],"Affects":[{"VehicleJourneys":[{"AffectedVehicleJourney":[{"LineRef":["\r\n                      MTA NYCT_6"],"DirectionRef":["1"]}]}]}],"Consequences":[{"Consequence":[{"Condition":["diverted"],"Severity":["undefined"]}]}]},{"CreationTime":["2018-07-16T00:00:00-04:00"],"SituationNumber":["\r\n                  MTA NYCT_192668"],"PublicationWindow":[{"StartTime":["2018-07-16T00:00:00-04:00"],"EndTime":["2018-07-27T23:59:00-04:00"]}],"Summary":[{"_":"TRACK MAINTENANCE  Jul 18 - 20, Wed to Fri","$":{"xml:lang":"EN"}}],"Description":[{"_":"TRACK MAINTENANCE  Jul 18 - 20, Wed to Fri","$":{"xml:lang":"EN"}}],"LongDescription":["<a class=\"plannedWorkDetailLink\" onclick=ShowHide(192668);><b>TRACK MAINTENANCE | Jul 18 - 20, Wed to Fri  </b>&bull;  <b>Jul 23 - 27, Mon to Fri, 10 AM to 3:30 PM<br clear=left>The last stop for alternate [6] trains headed toward Pelham Bay Park is 3 Av-138 St in the Bronx</a><br/><br/><div id= 192668 class=\"plannedWorkDetail\" ><br></b>          <a href=http://apps.mta.info/traintime/ target=_blank><img height=26px src=http://apps.mta.info/traintime/desktop2Images/logoSm.png></a><br>      <br></font><table class=plannedworkTableStyle  border=1 cellspacing=1 cellpadding=5 rules=none frame=box><td>  [ad]  <td><font size=1>This service change affects one or more ADA accessible stations. Please call 511 for help with planning your trip. If you are deaf or hard of hearing, use your preferred relay service provider or the free 711 relay.  </font></table><br><b><br></div></b><br/>"],"Planned":["true"],"ReasonName":["Planned Work"],"MessagePriority":["\r\n                  1\r\n                "],"Source":[{"SourceType":["directReport"]}],"Affects":[{"VehicleJourneys":[{"AffectedVehicleJourney":[{"LineRef":["\r\n                      MTA NYCT_6"],"DirectionRef":["0"]}]}]}],"Consequences":[{"Consequence":[{"Condition":["noService"],"Severity":["undefined"]}]}]},{"CreationTime":["2018-07-09T00:00:00-04:00"],"SituationNumber":["\r\n                  MTA NYCT_193549"],"PublicationWindow":[{"StartTime":["2018-07-09T00:00:00-04:00"],"EndTime":["2018-07-27T23:59:00-04:00"]}],"Summary":[{"_":"TRACK REPLACEMENT  Until Jul 27, Mon to Fri, 6 AM to 10 AM and 3 PM to 10 PM [7D] Express trains make local stops in both directions at 33, 40, 46, 52, 69 and 74 Sts","$":{"xml:lang":"EN"}}],"Description":[{"_":"TRACK REPLACEMENT  Until Jul 27, Mon to Fri, 6 AM to 10 AM and 3 PM to 10 PM [7D] Express trains make local stops in both directions at 33, 40, 46, 52, 69 and 74 Sts","$":{"xml:lang":"EN"}}],"LongDescription":["<a class=\"plannedWorkDetailLink\" onclick=ShowHide(193549);><b>TRACK REPLACEMENT | Until Jul 27, Mon to Fri, 6 AM to 10 AM and 3 PM to 10 PM<br clear=left>[7D] Express trains make local stops in both directions at 33, 40, 46, 52, 69 and 74 Sts</a><br/><br/><div id= 193549 class=\"plannedWorkDetail\" ><br></b>Rush hour [7D] express service runs between Mets-Willets Point and 74 St-Broadway<br><br>For Midtown Manhattan, consider [E] and [F] service via transfer at 74 St-Broadway/Roosevelt Av.<br><b><br></div></b><br/>"],"Planned":["true"],"ReasonName":["Planned Work"],"MessagePriority":["\r\n                  1\r\n                "],"Source":[{"SourceType":["directReport"]}],"Affects":[{"VehicleJourneys":[{"AffectedVehicleJourney":[{"LineRef":["\r\n                      MTA NYCT_7"],"DirectionRef":["0"]},{"LineRef":["\r\n                      MTA NYCT_7"],"DirectionRef":["1"]}]}]}],"Consequences":[{"Consequence":[{"Condition":["altered"],"Severity":["undefined"]}]}]},{"CreationTime":["2018-07-01T00:00:00-04:00"],"SituationNumber":["\r\n                  MTA NYCT_191353"],"PublicationWindow":[{"StartTime":["2018-07-01T00:00:00-04:00"],"EndTime":["2018-09-03T23:59:00-04:00"]}],"Summary":[{"_":"ROCKAWAYS FLOOD PROTECTION  Until September 3, 2018 No [A] trains running to Far Rockaway-Mott Av No [S] Rockaway Park Shuttle service at Broad Channel","$":{"xml:lang":"EN"}}],"Description":[{"_":"ROCKAWAYS FLOOD PROTECTION  Until September 3, 2018 No [A] trains running to Far Rockaway-Mott Av No [S] Rockaway Park Shuttle service at Broad Channel","$":{"xml:lang":"EN"}}],"LongDescription":["<a class=\"plannedWorkDetailLink\" onclick=ShowHide(191353);><b>ROCKAWAYS: FLOOD PROTECTION | Until September 3, 2018<br clear=left>No [A] trains running to Far Rockaway-Mott Av<br clear=left>No [S] Rockaway Park Shuttle service at Broad Channel</a><br/><br/><div id= 191353 class=\"plannedWorkDetail\" ><br></b>[A] trains run between <b>Inwood-207 St</b>, Manhattan and <b>Rockaway Park-Beach 116 St</b>, Queens.<br><br>The [S] Rockaway Park Shuttle runs, approximately <i>every 15 minutes,</i> between <b>Rockaway Park-Beach 116 St</b> and <b>Beach 90 St</b> and via the [A]  <i>to/from</i> <b>Far Rockaway-Mott Av</b>.<br><br>For <b>Far Rockaway-Mott Av</b> service, take the [S] instead, transfer at Beach 90 St.<br><br>For <b>Broad Channel</b> [S] shuttle customers, take the [A] instead.<br><br>[ad]  For an accessible connection between the [A] train and [S] shuttle trains, transfer at <b>Rockaway Park-Beach 116 St</b></font>.<br><b><br></div></b><br/>"],"Planned":["true"],"ReasonName":["Planned Work"],"MessagePriority":["\r\n                  1\r\n                "],"Source":[{"SourceType":["directReport"]}],"Affects":[{"VehicleJourneys":[{"AffectedVehicleJourney":[{"LineRef":["\r\n                      MTA NYCT_A"],"DirectionRef":["1"]},{"LineRef":["\r\n                      MTA NYCT_A"],"DirectionRef":["0"]},{"LineRef":["\r\n                      MTA NYCT_H"],"DirectionRef":["1"]},{"LineRef":["\r\n                      MTA NYCT_H"],"DirectionRef":["0"]}]}]}],"Consequences":[{"Consequence":[{"Condition":["diverted"],"Severity":["undefined"]}]}]},{"CreationTime":["2018-07-23T00:00:00-04:00"],"SituationNumber":["\r\n                  MTA NYCT_193501"],"PublicationWindow":[{"StartTime":["2018-07-23T00:00:00-04:00"],"EndTime":["2018-08-03T23:59:00-04:00"]}],"Summary":[{"_":"TRACK MAINTENANCE  Jul 23 - 27","$":{"xml:lang":"EN"}}],"Description":[{"_":"TRACK MAINTENANCE  Jul 23 - 27","$":{"xml:lang":"EN"}}],"LongDescription":["<a class=\"plannedWorkDetailLink\" onclick=ShowHide(193501);><b>TRACK MAINTENANCE | Jul 23 - 27  </b>&bull;<b>  Jul 30 - Aug 3, Mon to Fri, 9:45 AM to 3:30 PM<br clear=left>Brighton Beach-bound [B] trains run local from Prospect Park to Sheepshead Bay in Brooklyn</a><br/><br/><div id= 193501 class=\"plannedWorkDetail\" ><br></div></b><br/>"],"Planned":["true"],"ReasonName":["Planned Work"],"MessagePriority":["\r\n                  1\r\n                "],"Source":[{"SourceType":["directReport"]}],"Affects":[{"VehicleJourneys":[{"AffectedVehicleJourney":[{"LineRef":["\r\n                      MTA NYCT_B"],"DirectionRef":["1"]}]}]}],"Consequences":[{"Consequence":[{"Condition":["altered"],"Severity":["undefined"]}]}]},{"CreationTime":["2018-07-09T00:00:00-04:00"],"SituationNumber":["\r\n                  MTA NYCT_190053"],"PublicationWindow":[{"StartTime":["2018-07-09T00:00:00-04:00"],"EndTime":["2018-08-17T23:59:00-04:00"]}],"Summary":[{"_":"Rush Hour  Until Aug 17, Mon to Fri,  730 AM to 930 AM Additional [G] service operates between Court Sq and Bedford-Nostrand Avs","$":{"xml:lang":"EN"}}],"Description":[{"_":"Rush Hour  Until Aug 17, Mon to Fri,  730 AM to 930 AM Additional [G] service operates between Court Sq and Bedford-Nostrand Avs","$":{"xml:lang":"EN"}}],"LongDescription":["<a class=\"plannedWorkDetailLink\" onclick=ShowHide(190053);><b>Rush Hour | Until Aug 17, Mon to Fri,  7:30 AM to 9:30 AM<br clear=left>Additional [G] service operates between Court Sq and Bedford-Nostrand Avs</a><br/><br/><div id= 190053 class=\"plannedWorkDetail\" ><br></div></b><br/>"],"Planned":["true"],"ReasonName":["Planned Work"],"MessagePriority":["\r\n                  1\r\n                "],"Source":[{"SourceType":["directReport"]}],"Affects":[{"VehicleJourneys":[{"AffectedVehicleJourney":[{"LineRef":["\r\n                      MTA NYCT_G"],"DirectionRef":["1"]}]}]}],"Consequences":[{"Consequence":[{"Condition":["altered"],"Severity":["undefined"]}]}]},{"CreationTime":["2018-07-23T00:00:00-04:00"],"SituationNumber":["\r\n                  MTA NYCT_193500"],"PublicationWindow":[{"StartTime":["2018-07-23T00:00:00-04:00"],"EndTime":["2018-08-03T23:59:00-04:00"]}],"Summary":[{"_":"TRACK REPLACEMENT  Jul 23 - 27","$":{"xml:lang":"EN"}}],"Description":[{"_":"TRACK REPLACEMENT  Jul 23 - 27","$":{"xml:lang":"EN"}}],"LongDescription":["<a class=\"plannedWorkDetailLink\" onclick=ShowHide(193500);><b>TRACK REPLACEMENT | Jul 23 - 27  </b>&bull;<b>  Jul 30 - Aug 3, Mon to Fri, 9:45 AM to 3:30 PM<br clear=left>96 St-bound [Q] trains run express from Sheepshead Bay to Prospect Park in Brooklyn</a><br/><br/><div id= 193500 class=\"plannedWorkDetail\" ><br></b>Trains stop at Kings Hwy, Newkirk Plaza and Church Av.<br><br>For service <i>to </i>Neck Rd, Avenue U,<i> </i>Avenue M, Avenue J, Avenue H, Cortelyou, Beverley Rds and Parkside Av, take  the [Q] to Kings Hwy, Newkirk Plaza, Church Av or Prospect Park and transfer to a Brighton Beach-bound [B]* or Coney Island-bound [Q].<br><br>For service <i>from </i>these stations, take the [B] or [Q] to Church Av, Newkirk Plaza, Kings Hwy or Sheepshead Bay and transfer to a 96 St-bound [Q].<br><br><i>*This detour has taken into account additional planned service changes.<br></i><b><br></div></b><br/>"],"Planned":["true"],"ReasonName":["Planned Work"],"MessagePriority":["\r\n                  1\r\n                "],"Source":[{"SourceType":["directReport"]}],"Affects":[{"VehicleJourneys":[{"AffectedVehicleJourney":[{"LineRef":["\r\n                      MTA NYCT_Q"],"DirectionRef":["0"]}]}]}],"Consequences":[{"Consequence":[{"Condition":["diverted"],"Severity":["undefined"]}]}]},{"CreationTime":["2018-07-23T00:00:00-04:00"],"SituationNumber":["\r\n                  MTA NYCT_195737"],"PublicationWindow":[{"StartTime":["2018-07-23T00:00:00-04:00"],"EndTime":["2018-07-27T23:59:00-04:00"]}],"Summary":[{"_":"SCHEDULED MAINTENANCE  Jul 23 - 27, Mon to Fri, 9 AM to 3 PM [SIR] Trains board at the St. George-bound platform from Prince's Bay to Arthur Kill Stations","$":{"xml:lang":"EN"}}],"Description":[{"_":"SCHEDULED MAINTENANCE  Jul 23 - 27, Mon to Fri, 9 AM to 3 PM [SIR] Trains board at the St. George-bound platform from Prince's Bay to Arthur Kill Stations","$":{"xml:lang":"EN"}}],"LongDescription":["<a class=\"plannedWorkDetailLink\" onclick=ShowHide(195737);><b>SCHEDULED MAINTENANCE | Jul 23 - 27, Mon to Fri, 9 AM to 3 PM<br clear=left>[SIR] Trains board at the St. George-bound platform from Prince's Bay to Arthur Kill Stations</a><br/><br/><div id= 195737 class=\"plannedWorkDetail\" ><br></b>&bull; Boarding change includes <b>Prince's Bay</b>, <b>Pleasant Plains</b>, <b>Richmond Valley</b> and <b>Arthur Kill Stations</b>.<br><b><br></div></b><br/>"],"Planned":["true"],"ReasonName":["Planned Work"],"MessagePriority":["\r\n                  1\r\n                "],"Source":[{"SourceType":["directReport"]}],"Affects":[{"VehicleJourneys":[{"AffectedVehicleJourney":[{"LineRef":["\r\n                      MTA NYCT_SI"],"DirectionRef":["1"]}]}]}],"Consequences":[{"Consequence":[{"Condition":["altered"],"Severity":["undefined"]}]}]},{"CreationTime":["2018-07-16T00:00:00-04:00"],"SituationNumber":["\r\n                  MTA NYCT_195184"],"PublicationWindow":[{"StartTime":["2018-07-16T00:00:00-04:00"],"EndTime":["2018-07-27T23:59:00-04:00"]}],"Summary":[{"_":"SCHEDULED MAINTENANCE  Jul 16 - 20","$":{"xml:lang":"EN"}}],"Description":[{"_":"SCHEDULED MAINTENANCE  Jul 16 - 20","$":{"xml:lang":"EN"}}],"LongDescription":["<a class=\"plannedWorkDetailLink\" onclick=ShowHide(195184);><b>SCHEDULED MAINTENANCE | Jul 16 - 20  </b>&bull;<b>  Jul 23 - 27, Mon to Fri, 9 AM to 3 PM<br clear=left>[SIR] Trains board at the Tottenville-bound platform from Jefferson Av to Old Town Stations</a><br/><br/><div id= 195184 class=\"plannedWorkDetail\" ><br></b>&bull; Boarding change includes <b>Jefferson Av</b>, <b>Dongan Hills</b>, and <b>Old Town Stations</b>. <br><b><br></div></b><br/>"],"Planned":["true"],"ReasonName":["Planned Work"],"MessagePriority":["\r\n                  1\r\n                "],"Source":[{"SourceType":["directReport"]}],"Affects":[{"VehicleJourneys":[{"AffectedVehicleJourney":[{"LineRef":["\r\n                      MTA NYCT_SI"],"DirectionRef":["0"]}]}]}],"Consequences":[{"Consequence":[{"Condition":["altered"],"Severity":["undefined"]}]}]}]}]}]}]}}