{"Siri":{"$":{"xmlns:ns2":"http://www.ifopt.org.uk/acsb","xmlns":"http://www.siri.org.uk/siri","xmlns:ns4":"http://datex2.eu/schema/1_0/1_0","xmlns:ns3":"http://www.ifopt.org.uk/ifopt"},"ServiceDelivery":[{"ResponseTimestamp":["2018-01-02T09:48:47.2559549-05:00"],"SituationExchangeDelivery":[{"ResponseTimestamp":["2018-01-02T09:48:47.2559549-05:00"],"Status":["true"],"Situations":[{"PtSituationElement":[{"CreationTime":["2018-01-02T09:27:39.61-05:00"],"SituationNumber":["\r\n                  MTA NYCT_461af785-50f2-4534-b521-2e61377ea59b"],"PublicationWindow":[{"StartTime":["2018-01-02T07:53:00-05:00"],"EndTime":["2018-01-02T09:50:00-05:00"]}],"Summary":[{"_":"Southbound [2] and [5] trains service changes and delays because of a train with mechanical problems at 3 Av-149 St.","$":{"xml:lang":"EN"}}],"Description":[{"_":"<P>Southbound [5] trains are running local from <STRONG>E 180 St</STRONG> to<STRONG> 3 Av-149 St</STRONG>.</P>\r\n<P>Expect delays on [2] and [5] trains in both directions.</P>\r\n<P>These service changes are because of an earlier incident involving&nbsp;a train with mechanical problems at <STRONG>3 Av-149 St</STRONG>.</P>\r\n<P>&nbsp;</P>\r\n<P>&nbsp;</P>\r\n<P>&nbsp;</P>","$":{"xml:lang":"EN"}}],"LongDescription":["Southbound [5] trains are running local from E 180 St to 3 Av-149 St.\r\nExpect delays on [2] and [5] trains in both directions.\r\nThese service changes are because of an earlier incident involving&nbsp;a train with mechanical problems at 3 Av-149 St.\r\n&nbsp;\r\n&nbsp;\r\n&nbsp;"],"Planned":["false"],"ReasonName":["Service Change"],"MessagePriority":["3"],"Source":[{"SourceType":["directReport"]}],"Affects":[{"VehicleJourneys":[{"AffectedVehicleJourney":[{"LineRef":["\r\n                      MTA NYCT_2"],"DirectionRef":["1"]},{"LineRef":["\r\n                      MTA NYCT_5"],"DirectionRef":["1"]}]}]}],"Consequences":[{"Consequence":[{"Condition":["altered"],"Severity":["undefined"]}]}]},{"CreationTime":["2018-01-02T09:48:23.82-05:00"],"SituationNumber":["\r\n                  MTA NYCT_598112f9-5c1c-4805-a99b-0fbb1dcfbf6a"],"PublicationWindow":[{"StartTime":["2018-01-02T09:40:00-05:00"],"EndTime":["2018-01-02T10:00:00-05:00"]}],"Summary":[{"_":"[4] and [5] train service has resumed following an earlier incident involving a sick passenger at Bowling Green.","$":{"xml:lang":"EN"}}],"Description":[{"_":"[4] and [5] train service has resumed following an earlier incident involving a sick passenger at <STRONG>Bowling Green.</STRONG>","$":{"xml:lang":"EN"}}],"LongDescription":["[4] and [5] train service has resumed following an earlier incident involving a sick passenger at Bowling Green."],"Planned":["false"],"ReasonName":["Delays"],"MessagePriority":["2"],"Source":[{"SourceType":["directReport"]}],"Affects":[{"VehicleJourneys":[{"AffectedVehicleJourney":[{"LineRef":["\r\n                      MTA NYCT_4"],"DirectionRef":["1"]},{"LineRef":["\r\n                      MTA NYCT_5"],"DirectionRef":["1"]}]}]}],"Consequences":[{"Consequence":[{"Condition":["delayed"],"Severity":["undefined"]}]}]},{"CreationTime":["2018-01-02T09:31:12.813-05:00"],"SituationNumber":["\r\n                  MTA NYCT_1995532c-91a9-4679-9626-a6b3891e7084"],"PublicationWindow":[{"StartTime":["2018-01-02T09:29:00-05:00"]}],"Summary":[{"_":"Southbound [D] trains are running with delays because of signal problems at Bay Parkway.","$":{"xml:lang":"EN"}}],"Description":[{"_":"Southbound [D] trains are running with delays because of signal problems at <STRONG>Bay Pkwy.</STRONG>","$":{"xml:lang":"EN"}}],"LongDescription":["Southbound [D] trains are running with delays because of signal problems at Bay Pkwy."],"Planned":["false"],"ReasonName":["Delays"],"MessagePriority":["2"],"Source":[{"SourceType":["directReport"]}],"Affects":[{"VehicleJourneys":[{"AffectedVehicleJourney":[{"LineRef":["\r\n                      MTA NYCT_D"],"DirectionRef":["1"]}]}]}],"Consequences":[{"Consequence":[{"Condition":["delayed"],"Severity":["undefined"]}]}]},{"CreationTime":["2018-01-02T09:16:21.27-05:00"],"SituationNumber":["\r\n                  MTA NYCT_1d316a84-60e2-414f-a574-3cc9bae6b85f"],"PublicationWindow":[{"StartTime":["2018-01-02T08:15:00-05:00"]}],"Summary":[{"_":"Northbound [E] trains are running local from 75 Av to Briarwood-Van Wyck because of signal problems at Kew Gardens-Union Tpke.","$":{"xml:lang":"EN"}}],"Description":[{"_":"<P>Northbound [E] trains are running local from <STRONG>75 Av</STRONG> to <STRONG>Briarwood-Van Wyck</STRONG> because of signal problems at <STRONG>Kew Gardens-Union Tpke</STRONG>.</P>\r\n<P>Expect delays on [E] and [F] trains.</P>","$":{"xml:lang":"EN"}}],"LongDescription":["Northbound [E] trains are running local from 75 Av to Briarwood-Van Wyck because of signal problems at Kew Gardens-Union Tpke.\r\nExpect delays on [E] and [F] trains."],"Planned":["false"],"ReasonName":["Service Change"],"MessagePriority":["3"],"Source":[{"SourceType":["directReport"]}],"Affects":[{"VehicleJourneys":[{"AffectedVehicleJourney":[{"LineRef":["\r\n                      MTA NYCT_E"],"DirectionRef":["0"]},{"LineRef":["\r\n                      MTA NYCT_F"],"DirectionRef":["0"]},{"LineRef":["\r\n                      MTA NYCT_F"],"DirectionRef":["1"]}]}]}],"Consequences":[{"Consequence":[{"Condition":["altered"],"Severity":["undefined"]}]}]},{"CreationTime":["2018-01-02T09:47:17.847-05:00"],"SituationNumber":["\r\n                  MTA NYCT_2e8d96f9-d013-475a-bfa3-e7fe2835231b"],"PublicationWindow":[{"StartTime":["2018-01-02T09:40:00-05:00"]}],"Summary":[{"_":"Northbound [N] and [W] trains service changes and delays because of a train with mechanical problems at Queensboro Plaza.","$":{"xml:lang":"EN"}}],"Description":[{"_":"<P>Northbound [W] trains are stopping along the [Q] line from <STRONG>57 St-7 Av</STRONG> and end at <STRONG>96 St-2 Av.</STRONG></P>\r\n<P>Northbound [N] trains will end at<STRONG> Times Sq-42 St</STRONG>.</P>\r\n<P>This service changes are because of a train with mechanical problems at <STRONG>Queensboro Plaza.</STRONG></P>\r\n<P>Expect delays on [N], [Q], [R] and [W] trains.</P>","$":{"xml:lang":"EN"}}],"LongDescription":["Northbound [W] trains are stopping along the [Q] line from 57 St-7 Av and end at 96 St-2 Av.\r\nNorthbound [N] trains will end at Times Sq-42 St.\r\nThis service changes are because of a train with mechanical problems at Queensboro Plaza.\r\nExpect delays on [N], [Q], [R] and [W] trains."],"Planned":["false"],"ReasonName":["Service Change"],"MessagePriority":["3"],"Source":[{"SourceType":["directReport"]}],"Affects":[{"VehicleJourneys":[{"AffectedVehicleJourney":[{"LineRef":["\r\n                      MTA NYCT_N"],"DirectionRef":["0"]},{"LineRef":["\r\n                      MTA NYCT_W"],"DirectionRef":["0"]}]}]}],"Consequences":[{"Consequence":[{"Condition":["altered"],"Severity":["undefined"]}]}]},{"CreationTime":["2018-01-02T00:00:00-05:00"],"SituationNumber":["\r\n                  MTA NYCT_175168"],"PublicationWindow":[{"StartTime":["2018-01-02T00:00:00-05:00"],"EndTime":["2018-01-05T23:59:00-05:00"]}],"Summary":[{"_":"ELECTRICAL IMPROVEMENTS  [1] Van Cortlandt Park-bound trains skip 207, 215, 225, 231 and 238 Sts","$":{"xml:lang":"EN"}}],"Description":[{"_":"ELECTRICAL IMPROVEMENTS  [1] Van Cortlandt Park-bound trains skip 207, 215, 225, 231 and 238 Sts","$":{"xml:lang":"EN"}}],"LongDescription":["&lt;b&gt;&lt;i&gt;ELECTRICAL IMPROVEMENTS&lt;/i&gt;&lt;br clear=left&gt;[1] Van Cortlandt Park-bound trains skip 207, 215, 225, 231 and 238 Sts&lt;/b&gt;Days, 9:45 AM to 3:30 PM, &lt;/font&gt;Tue to Fri, Jan 2 - 5&lt;br&gt;&lt;br&gt;For service &lt;i&gt;to &lt;/i&gt;these stations, take the [1] to 242 St and transfer to a South Ferry-bound [1].&lt;br&gt;&lt;br&gt;For service &lt;i&gt;from &lt;/i&gt;207 and 215 Sts, take the [1] to Dyckman&lt;/font&gt; St and transfer to a&lt;br&gt;Van Cortlandt Park-bound [1].&lt;br&gt;&lt;br&gt;For service &lt;i&gt;from &lt;/i&gt;225, 231 and 238 Sts, take the &lt;a href=http://web.mta.info/nyct/bus/schedule/bronx/bx009cur.pdf target=blank&gt;&lt;font color=#0000FF&gt;Bx9&lt;/font&gt;&lt;/a&gt; bus.&lt;br&gt;&lt;br&gt;&lt;/font&gt;&lt;b&gt;&lt;i&gt;Alternate travel note:&lt;br&gt;&lt;/b&gt;&lt;/i&gt;For 207 St, consider the nearby &lt;a href=http://web.mta.info/weekender/tileMap.html?staID=10114 target=_blank&gt;&lt;font color=#0000FF&gt;207 St&lt;/font&gt;&lt;/a&gt; [A] Station via transfer at 168 St.&lt;br&gt;&lt;br&gt;&lt;table class=plannedworkTableStyle  border=1 cellspacing=1 cellpadding=5 rules=none frame=box&gt;&lt;td&gt;  [ad]  &lt;td&gt;&lt;font size=1&gt;This service change affects one or more ADA accessible stations. Please call 511 for help with planning&lt;br&gt;your trip. If you are deaf or hard of hearing, use your preferred relay service provider or the free 711 relay.  &lt;/font&gt;&lt;/table&gt;&lt;br&gt;&lt;b&gt;&lt;br&gt;"],"Planned":["true"],"ReasonName":["Planned Work"],"MessagePriority":["\r\n                  1\r\n                "],"Source":[{"SourceType":["directReport"]}],"Affects":[{"VehicleJourneys":[{"AffectedVehicleJourney":[{"LineRef":["\r\n                      MTA NYCT_1"],"DirectionRef":["0"]}]}]}],"Consequences":[{"Consequence":[{"Condition":["diverted"],"Severity":["undefined"]}]}]},{"CreationTime":["2017-12-26T00:00:00-05:00"],"SituationNumber":["\r\n                  MTA NYCT_174461"],"PublicationWindow":[{"StartTime":["2017-12-26T00:00:00-05:00"],"EndTime":["2018-01-05T23:59:00-05:00"]}],"Summary":[{"_":"ELECTRICAL IMPROVEMENTS  [4] Crown Hts-bound trains run express from Mosholu Pkwy to 149 St-Grand Concourse","$":{"xml:lang":"EN"}}],"Description":[{"_":"ELECTRICAL IMPROVEMENTS  [4] Crown Hts-bound trains run express from Mosholu Pkwy to 149 St-Grand Concourse","$":{"xml:lang":"EN"}}],"LongDescription":["&lt;b&gt;&lt;i&gt;ELECTRICAL IMPROVEMENTS&lt;/i&gt;&lt;br clear=left&gt;[4] Crown Hts-bound trains run express from Mosholu Pkwy to 149 St-Grand Concourse&lt;/b&gt;Days, 9:45 AM to 3:30 PM, Tue to Fri, Jan 2 - 5&lt;br&gt;&lt;br&gt;No Crown Hts-bound service at &lt;b&gt;Bedford Park Blvd&lt;/b&gt;, &lt;b&gt;Kingsbridge Rd&lt;/b&gt;, &lt;b&gt;Fordham Rd&lt;/b&gt;, &lt;b&gt;183 St&lt;/b&gt;, &lt;b&gt;176 St&lt;/b&gt;,&lt;br&gt;&lt;b&gt;Mt Eden Av&lt;/b&gt;, &lt;b&gt;170&lt;/b&gt;, &lt;b&gt;167&lt;/b&gt; and &lt;b&gt;161 Sts&lt;/b&gt;.&lt;br&gt;&lt;br&gt;&lt;table class=plannedworkTableStyle  width=90%&gt;&lt;tr&gt;&lt;td&gt;&lt;font size=3&gt;&lt;b&gt;Travel Alternatives&lt;/b&gt;&lt;/font&gt;&lt;td align=right&gt;[TP]&lt;/table&gt;&lt;br&gt;For service &lt;i&gt;to&lt;/i&gt; Bedford Park Blvd, Kingsbridge Rd, Fordham Rd and 183 St, take the [4] to Burnside Av&lt;br&gt;and transfer to a Woodlawn-bound [4].&lt;br&gt;&lt;br&gt;For service &lt;i&gt;to&lt;/i&gt; 176 St, Mt Eden Av, 170, 167 and 161 Sts, take the [4] to 149 St-Grand Concourse&lt;br&gt;and transfer to a Woodlawn-bound [4].&lt;br&gt;&lt;br&gt;For service &lt;i&gt;from&lt;/i&gt; these stations, take the [4] to Burnside Av or Mosholu Pkwy and transfer to a&lt;br&gt;Crown Hts-bound [4].&lt;br&gt;&lt;br&gt;&lt;table class=plannedworkTableStyle  border=1 cellspacing=1 cellpadding=5 rules=none frame=box&gt;&lt;td&gt;  [ad]  &lt;td&gt;&lt;font size=1&gt;This service change affects one or more ADA accessible stations. Please call 511 for help with planning&lt;br&gt;your trip. If you are deaf or hard of hearing, use your preferred relay service provider or the free 711 relay.  &lt;/font&gt;&lt;/table&gt;&lt;br&gt;&lt;b&gt;&lt;br&gt;"],"Planned":["true"],"ReasonName":["Planned Work"],"MessagePriority":["\r\n                  1\r\n                "],"Source":[{"SourceType":["directReport"]}],"Affects":[{"VehicleJourneys":[{"AffectedVehicleJourney":[{"LineRef":["\r\n                      MTA NYCT_4"],"DirectionRef":["1"]}]}]}],"Consequences":[{"Consequence":[{"Condition":["diverted"],"Severity":["undefined"]}]}]},{"CreationTime":["2018-01-02T00:00:00-05:00"],"SituationNumber":["\r\n                  MTA NYCT_175038"],"PublicationWindow":[{"StartTime":["2018-01-02T00:00:00-05:00"],"EndTime":["2018-01-05T23:59:00-05:00"]}],"Summary":[{"_":"TRACK REPLACEMENT  [7] Hudson Yards-bound trains skip 111, 103, 90 and 82 Sts","$":{"xml:lang":"EN"}}],"Description":[{"_":"TRACK REPLACEMENT  [7] Hudson Yards-bound trains skip 111, 103, 90 and 82 Sts","$":{"xml:lang":"EN"}}],"LongDescription":["&lt;b&gt;&lt;i&gt;TRACK REPLACEMENT&lt;/i&gt;&lt;br clear=left&gt;[7] Hudson Yards-bound trains skip 111, 103, 90 and 82 Sts&lt;/b&gt;Days, 9:45 AM to 3:30 PM, Tue to Fri, Jan 2 - 5&lt;br&gt;&lt;br&gt;&lt;/font&gt;For service&lt;i&gt; to&lt;/i&gt; these stations, take the [7] to Junction Blvd or 74 St &lt;br&gt;and transfer to a Flushing-bound [7].&lt;br&gt;&lt;br&gt;For service &lt;i&gt;from&lt;/i&gt; these stations, take the [7] to Junction Blvd or Willets Point&lt;br&gt;and transfer to a Hudson Yards-bound [7].&lt;br&gt;&lt;b&gt;&lt;br&gt;"],"Planned":["true"],"ReasonName":["Planned Work"],"MessagePriority":["\r\n                  1\r\n                "],"Source":[{"SourceType":["directReport"]}],"Affects":[{"VehicleJourneys":[{"AffectedVehicleJourney":[{"LineRef":["\r\n                      MTA NYCT_7"],"DirectionRef":["1"]}]}]}],"Consequences":[{"Consequence":[{"Condition":["diverted"],"Severity":["undefined"]}]}]},{"CreationTime":["2018-01-02T00:00:00-05:00"],"SituationNumber":["\r\n                  MTA NYCT_175054"],"PublicationWindow":[{"StartTime":["2018-01-02T00:00:00-05:00"],"EndTime":["2018-01-05T23:59:00-05:00"]}],"Summary":[{"_":"TRACK REPLACEMENT  [7] Flushing-bound trains skip 33, 40, 46, 52 and 69 Sts","$":{"xml:lang":"EN"}}],"Description":[{"_":"TRACK REPLACEMENT  [7] Flushing-bound trains skip 33, 40, 46, 52 and 69 Sts","$":{"xml:lang":"EN"}}],"LongDescription":["&lt;b&gt;&lt;i&gt;TRACK REPLACEMENT&lt;/i&gt;&lt;br clear=left&gt;[7] Flushing-bound trains skip 33, 40, 46, 52 and 69 Sts&lt;/b&gt;&lt;/font&gt;Days, 9:45 AM to 3:30 PM, Tue to Fri, Jan 2 - 5&lt;/font&gt; &lt;br&gt;&lt;br&gt;For service &lt;i&gt;to&lt;/i&gt; these stations, take the [7] to 61 St-Woodside or 74 St and &lt;br&gt;transfer to a Hudson Yards-bound [7].&lt;br&gt;&lt;br&gt;For service &lt;i&gt;from&lt;/i&gt; these stations, take the [7] to 61 St-Woodside or Queensboro Plaza &lt;br&gt;and transfer to a Flushing-bound [7].&lt;br&gt;&lt;b&gt;&lt;br&gt;"],"Planned":["true"],"ReasonName":["Planned Work"],"MessagePriority":["\r\n                  1\r\n                "],"Source":[{"SourceType":["directReport"]}],"Affects":[{"VehicleJourneys":[{"AffectedVehicleJourney":[{"LineRef":["\r\n                      MTA NYCT_7"],"DirectionRef":["0"]}]}]}],"Consequences":[{"Consequence":[{"Condition":["diverted"],"Severity":["undefined"]}]}]},{"CreationTime":["2018-01-02T00:00:00-05:00"],"SituationNumber":["\r\n                  MTA NYCT_175348"],"PublicationWindow":[{"StartTime":["2018-01-02T00:00:00-05:00"],"EndTime":["2018-01-04T23:59:00-05:00"]}],"Summary":[{"_":"SIGNAL MAINTENANCE  [F] Coney Island-bound trains skip 169 St, Sutphin Blvd, Briarwood and 75 Av","$":{"xml:lang":"EN"}}],"Description":[{"_":"SIGNAL MAINTENANCE  [F] Coney Island-bound trains skip 169 St, Sutphin Blvd, Briarwood and 75 Av","$":{"xml:lang":"EN"}}],"LongDescription":["&lt;b&gt;&lt;i&gt;SIGNAL MAINTENANCE&lt;/i&gt;&lt;br clear=left&gt;[F] Coney Island-bound trains skip 169 St, Sutphin Blvd, Briarwood and 75 Av&lt;/b&gt;Days, 9:45 AM to 3:30 PM, Tue to Thu, Jan 2 - 4&lt;br&gt;&lt;br&gt;&lt;/font&gt;For service &lt;i&gt;to &lt;/i&gt;169 St, take a &lt;a href=http://web.mta.info/nyct/bus/schedule/queens/q001cur.pdf target=_blank&gt;&lt;font color=#0000FF&gt;Q1&lt;/font&gt;&lt;/a&gt;, &lt;a href=http://web.mta.info/nyct/bus/schedule/queens/q002cur.pdf target=_blank&gt;&lt;font color=#0000FF&gt;Q2&lt;/font&gt;&lt;/a&gt;, &lt;a href=http://web.mta.info/nyct/bus/schedule/queens/q003cur.pdf target=_blank&gt;&lt;font color=#0000FF&gt;Q3&lt;/font&gt;&lt;/a&gt;, &lt;a href=http://web.mta.info/nyct/bus/schedule/queens/q017cur.pdf target=_blank&gt;&lt;font color=#0000FF&gt;Q17&lt;/font&gt;&lt;/a&gt; or &lt;a href=http://web.mta.info/nyct/bus/schedule/queens/q036cur.pdf target=_blank&gt;&lt;font color=#0000FF&gt;Q36&lt;/font&gt;&lt;/a&gt; bus instead.&lt;br&gt;&lt;br&gt;For service &lt;i&gt;to&lt;/i&gt; Sutphin Blvd, Briarwood and 75 Av, take the [F] to Union Tpke or 71 Av and transfer to a&lt;br&gt;Jamaica-bound [F].&lt;br&gt;&lt;br&gt;For service &lt;i&gt;from&lt;/i&gt; these stations, take the [F] to Union Tpke, Parsons Blvd or 179 St and transfer to a &lt;br&gt;Coney Island-bound [F].&lt;br&gt;&lt;b&gt;&lt;br&gt;"],"Planned":["true"],"ReasonName":["Planned Work"],"MessagePriority":["\r\n                  1\r\n                "],"Source":[{"SourceType":["directReport"]}],"Affects":[{"VehicleJourneys":[{"AffectedVehicleJourney":[{"LineRef":["\r\n                      MTA NYCT_F"],"DirectionRef":["1"]}]}]}],"Consequences":[{"Consequence":[{"Condition":["diverted"],"Severity":["undefined"]}]}]},{"CreationTime":["2018-01-02T00:00:00-05:00"],"SituationNumber":["\r\n                  MTA NYCT_175329"],"PublicationWindow":[{"StartTime":["2018-01-02T00:00:00-05:00"],"EndTime":["2018-01-05T23:59:00-05:00"]}],"Summary":[{"_":"TRACK REPLACEMENT  Broad St-bound [J] and Forest Hills-bound [M] trains skip Flushing Av, Lorimer St and Hewes St","$":{"xml:lang":"EN"}}],"Description":[{"_":"TRACK REPLACEMENT  Broad St-bound [J] and Forest Hills-bound [M] trains skip Flushing Av, Lorimer St and Hewes St","$":{"xml:lang":"EN"}}],"LongDescription":["&lt;b&gt;&lt;i&gt;TRACK REPLACEMENT&lt;/i&gt;&lt;br clear=left&gt;Broad St-bound [J] and Forest Hills-bound [M] trains skip Flushing Av, Lorimer St and Hewes St&lt;/b&gt;Days, 9:45 AM to 3:30 PM, Tue to Fri, &lt;/font&gt;Jan 2 - 5&lt;br&gt;&lt;br&gt;For service &lt;i&gt;to&lt;/i&gt; these stations, take the [J] or [M] to Essex St* and transfer to a &lt;br&gt;Jamaica Center-bound [J] or Brooklyn-bound [M].&lt;br&gt;&lt;br&gt;For service&lt;i&gt; from&lt;/i&gt; these stations, take the [J] or [M] to Myrtle Av and transfer to a &lt;br&gt;Broad St-bound [J] or Forest Hills-bound [M].&lt;br&gt;&lt;br&gt;&lt;i&gt;*Transfer at Marcy Av with &lt;a href=http://web.mta.info/metrocard/mcgtreng.htm#unlimited target=_blank&gt;&lt;font color=#0000FF&gt;Unlimited Ride MetroCard&lt;/font&gt;&lt;/a&gt;.&lt;br&gt;&lt;br&gt;&lt;b&gt;Alternate travel note:&lt;br&gt;&lt;/b&gt;&lt;/i&gt;Take the &lt;a href=http://web.mta.info/nyct/bus/schedule/bkln/b046cur.pdf target=_blank&gt;&lt;font color=#0000FF&gt;B46&lt;/font&gt;&lt;/a&gt; bus via transfer at Myrtle Av or Marcy Av.&lt;br&gt;&lt;br&gt;&lt;table class=plannedworkTableStyle  border=1 cellspacing=1 cellpadding=5 rules=none frame=box&gt;&lt;td&gt;  [ad]  &lt;td&gt;&lt;font size=1&gt;This service change affects one or more ADA accessible stations. Please call 511 for help with planning&lt;br&gt;your trip. If you are deaf or hard of hearing, use your preferred relay service provider or the free 711 relay.  &lt;/font&gt;&lt;/table&gt;&lt;br&gt;&lt;b&gt;&lt;br&gt;"],"Planned":["true"],"ReasonName":["Planned Work"],"MessagePriority":["\r\n                  1\r\n                "],"Source":[{"SourceType":["directReport"]}],"Affects":[{"VehicleJourneys":[{"AffectedVehicleJourney":[{"LineRef":["\r\n                      MTA NYCT_J"],"DirectionRef":["1"]},{"LineRef":["\r\n                      MTA NYCT_M"],"DirectionRef":["0"]}]}]}],"Consequences":[{"Consequence":[{"Condition":["diverted"],"Severity":["undefined"]}]}]},{"CreationTime":["2018-01-02T00:00:00-05:00"],"SituationNumber":["\r\n                  MTA NYCT_177256"],"PublicationWindow":[{"StartTime":["2018-01-02T00:00:00-05:00"],"EndTime":["2018-01-05T23:59:00-05:00"]}],"Summary":[{"_":"SCHEDULED MAINTENANCE  [SIR] Trains board at the St. George-bound platform from Stapleton to Grasmere Stations","$":{"xml:lang":"EN"}}],"Description":[{"_":"SCHEDULED MAINTENANCE  [SIR] Trains board at the St. George-bound platform from Stapleton to Grasmere Stations","$":{"xml:lang":"EN"}}],"LongDescription":["&lt;b&gt;&lt;i&gt;SCHEDULED MAINTENANCE&lt;/i&gt;&lt;br clear=left&gt;[SIR] Trains board at the St. George-bound platform from Stapleton to Grasmere Stations&lt;/b&gt;Days, 9:30 AM to 3 PM, Tue to Fri, Jan 2 - 5&lt;br&gt;&lt;br&gt; Boarding change includes &lt;b&gt;Stapleton&lt;/b&gt;, &lt;b&gt;Clifton&lt;/b&gt; and &lt;b&gt;Grasmere Stations&lt;/b&gt;.&lt;br&gt;&lt;b&gt;&lt;br&gt;"],"Planned":["true"],"ReasonName":["Planned Work"],"MessagePriority":["\r\n                  1\r\n                "],"Source":[{"SourceType":["directReport"]}],"Affects":[{"VehicleJourneys":[{"AffectedVehicleJourney":[{"LineRef":["\r\n                      MTA NYCT_SI"],"DirectionRef":["1"]}]}]}],"Consequences":[{"Consequence":[{"Condition":["altered"],"Severity":["undefined"]}]}]}]}]}]}]}}