{"Siri":{"$":{"xmlns:ns2":"http://www.ifopt.org.uk/acsb","xmlns":"http://www.siri.org.uk/siri","xmlns:ns4":"http://datex2.eu/schema/1_0/1_0","xmlns:ns3":"http://www.ifopt.org.uk/ifopt"},"ServiceDelivery":[{"ResponseTimestamp":["2018-02-14T09:13:02.7487579-05:00"],"SituationExchangeDelivery":[{"ResponseTimestamp":["2018-02-14T09:13:02.7487579-05:00"],"Status":["true"],"Situations":[{"PtSituationElement":[{"CreationTime":["2018-02-14T09:08:38.303-05:00"],"SituationNumber":["\r\n                  MTA NYCT_28e340c9-9f3f-40c0-8421-74a57c2d7f45"],"PublicationWindow":[{"StartTime":["2018-02-14T08:38:00-05:00"],"EndTime":["2018-02-14T09:20:00-05:00"]}],"Summary":[{"_":"[E], [F] and [M] train service has resumed following an earlier incident involving a sick customer at Court Sq-23 St.","$":{"xml:lang":"EN"}}],"Description":[{"_":"[E], [F] and [M] train service has resumed following an earlier incident involving a sick customer at Court Sq-23 St.","$":{"xml:lang":"EN"}}],"LongDescription":["[E], [F] and [M] train service has resumed following an earlier incident involving a sick customer at Court Sq-23 St."],"Planned":["false"],"ReasonName":["Delays"],"MessagePriority":["2"],"Source":[{"SourceType":["directReport"]}],"Affects":[{"VehicleJourneys":[{"AffectedVehicleJourney":[{"LineRef":["\r\n                      MTA NYCT_E"],"DirectionRef":["1"]},{"LineRef":["\r\n                      MTA NYCT_F"],"DirectionRef":["1"]},{"LineRef":["\r\n                      MTA NYCT_M"],"DirectionRef":["1"]}]}]}],"Consequences":[{"Consequence":[{"Condition":["delayed"],"Severity":["undefined"]}]}]},{"CreationTime":["2018-02-14T08:46:41.553-05:00"],"SituationNumber":["\r\n                  MTA NYCT_f3061ae0-0b3c-43ce-8766-b4e19eacc00f"],"PublicationWindow":[{"StartTime":["2018-02-14T07:50:00-05:00"]}],"Summary":[{"_":"Southbound [E] and [F] train service is running with delays because of signal problems at 75 Av.","$":{"xml:lang":"EN"}}],"Description":[{"_":"Southbound [E] and [F] train service is running with delays because of signal problems at 75 Av.","$":{"xml:lang":"EN"}}],"LongDescription":["Some southbound [E] and [F] trains are running local from Kew Gardens-Union Tpke to Jackson Hts-Roosevelt Av because of&nbsp;signal problems at 75 Av.\r\nExpect delays on the [E], [F], [M] and [R] trains.\r\nOur crews are on scene working to fix it as soon as possible and we'll follow up soon. Stay tune for updates.\r\n&nbsp;"],"Planned":["false"],"ReasonName":["Service Change"],"MessagePriority":["3"],"Source":[{"SourceType":["directReport"]}],"Affects":[{"VehicleJourneys":[{"AffectedVehicleJourney":[{"LineRef":["\r\n                      MTA NYCT_E"],"DirectionRef":["1"]},{"LineRef":["\r\n                      MTA NYCT_F"],"DirectionRef":["1"]},{"LineRef":["\r\n                      MTA NYCT_M"],"DirectionRef":["1"]},{"LineRef":["\r\n                      MTA NYCT_R"],"DirectionRef":["1"]}]}]}],"Consequences":[{"Consequence":[{"Condition":["altered"],"Severity":["undefined"]}]}]},{"CreationTime":["2018-02-14T09:12:19.223-05:00"],"SituationNumber":["\r\n                  MTA NYCT_8105fcc3-8819-45d4-93cf-a091aa00bf9b"],"PublicationWindow":[{"StartTime":["2018-02-14T07:09:00-05:00"]}],"Summary":[{"_":"[G] trains are running with delays in both directions because of signal problems at Flushing Av","$":{"xml:lang":"EN"}}],"Description":[{"_":"[G] trains are running with delays in both directions because of signal problems at Flushing Av","$":{"xml:lang":"EN"}}],"LongDescription":["[G] trains are running with delays in both directions because of signal problems at Flushing Av.\r\nOur crews are on scene working to fix it as soon as possible and we'll follow up soon. Stay tune for updates.\r\n&nbsp;"],"Planned":["false"],"ReasonName":["Delays"],"MessagePriority":["2"],"Source":[{"SourceType":["directReport"]}],"Affects":[{"VehicleJourneys":[{"AffectedVehicleJourney":[{"LineRef":["\r\n                      MTA NYCT_G"],"DirectionRef":["1"]}]}]}],"Consequences":[{"Consequence":[{"Condition":["delayed"],"Severity":["undefined"]}]}]},{"CreationTime":["2018-02-12T00:00:00-05:00"],"SituationNumber":["\r\n                  MTA NYCT_181013"],"PublicationWindow":[{"StartTime":["2018-02-12T00:00:00-05:00"],"EndTime":["2018-02-16T23:59:00-05:00"]}],"Summary":[{"_":"SCHEDULED MAINTENANCE  [SIR] Service runs on an adjusted schedule in both directions","$":{"xml:lang":"EN"}}],"Description":[{"_":"SCHEDULED MAINTENANCE  [SIR] Service runs on an adjusted schedule in both directions","$":{"xml:lang":"EN"}}],"LongDescription":["&lt;b&gt;&lt;i&gt;SCHEDULED MAINTENANCE&lt;/i&gt;&lt;br clear=left&gt;[SIR] Service runs on an adjusted schedule in both directions&lt;/b&gt;Days, 9 AM to 3 PM, Mon to Fri, Feb 12 - 16&lt;br&gt;&lt;br&gt; Tottenville-bound trains depart 2 minutes &lt;i&gt;later&lt;/i&gt; than regularly scheduled.&lt;br&gt;&lt;br&gt; St George-bound trains depart 5 minutes &lt;i&gt;earlier&lt;/i&gt; than regularly scheduled.&lt;br&gt;&lt;b&gt;&lt;/b&gt;          &lt;/font&gt;&lt;a href=http://apps.mta.info/traintime/ target=_blank&gt;&lt;img height=32px src=http://apps.mta.info/traintime/desktop2Images/logoSm.png&gt;&lt;/a&gt;&lt;br&gt;"],"Planned":["true"],"ReasonName":["Planned Work"],"MessagePriority":["\r\n                  1\r\n                "],"Source":[{"SourceType":["directReport"]}],"Affects":[{"VehicleJourneys":[{"AffectedVehicleJourney":[{"LineRef":["\r\n                      MTA NYCT_SI"],"DirectionRef":["1"]},{"LineRef":["\r\n                      MTA NYCT_SI"],"DirectionRef":["0"]}]}]}],"Consequences":[{"Consequence":[{"Condition":["altered"],"Severity":["undefined"]}]}]}]}]}]}]}}